python_classy/__init__.py
python_classy/mutability.py
python_classy-0.0.2.dist-info/LICENSE
python_classy-0.0.2.dist-info/METADATA
python_classy-0.0.2.dist-info/WHEEL
python_classy-0.0.2.dist-info/RECORD
