Metadata-Version: 2.1
Name: python-classy
Version: 0.0.2
Summary: Yet another simple dataclass-like object for python.
License: MIT
Author: 백세종
Author-email: sejong418@icloud.com
Requires-Python: >=3.11,<3.12
Classifier: License :: OSI Approved :: MIT License
Classifier: Programming Language :: Python :: 3
Classifier: Programming Language :: Python :: 3.11
